libralm_mcp_server.py
libralm_mcp_server-0.1.2.dist-info/METADATA
libralm_mcp_server-0.1.2.dist-info/WHEEL
libralm_mcp_server-0.1.2.dist-info/entry_points.txt
libralm_mcp_server-0.1.2.dist-info/licenses/LICENSE
libralm_mcp_server-0.1.2.dist-info/RECORD
