Metadata-Version: 2.4
Name: libralm-mcp-server
Version: 0.1.2
Summary: LibraLM MCP Server - A Model Context Protocol server for searching and retrieving book information
Project-URL: Homepage, https://github.com/libralm-ai/libralm_mcp_server
Project-URL: Documentation, https://github.com/libralm-ai/libralm_mcp_server#readme
Project-URL: Repository, https://github.com/libralm-ai/libralm_mcp_server
Project-URL: Issues, https://github.com/libralm-ai/libralm_mcp_server/issues
Author-email: LibraLM <support@libralm.com>
License: MIT
License-File: LICENSE
Keywords: books,libralm,library,mcp,search,server
Classifier: Development Status :: 4 - Beta
Classifier: Intended Audience :: Developers
Classifier: License :: OSI Approved :: MIT License
Classifier: Programming Language :: Python :: 3
Classifier: Programming Language :: Python :: 3.10
Classifier: Programming Language :: Python :: 3.11
Classifier: Programming Language :: Python :: 3.12
Classifier: Topic :: Software Development :: Libraries :: Python Modules
Requires-Python: >=3.10
Requires-Dist: fastmcp>=2.11.0
Requires-Dist: mcp>=1.12.3
Requires-Dist: pydantic>=2.11.7
Requires-Dist: requests>=2.32.4
